notebook_as_pdf_abirami/__init__.py
notebook_as_pdf_abirami-0.5.8.dist-info/LICENSE
notebook_as_pdf_abirami-0.5.8.dist-info/METADATA
notebook_as_pdf_abirami-0.5.8.dist-info/WHEEL
notebook_as_pdf_abirami-0.5.8.dist-info/entry_points.txt
notebook_as_pdf_abirami-0.5.8.dist-info/top_level.txt
notebook_as_pdf_abirami-0.5.8.dist-info/RECORD
