Metadata-Version: 2.1
Name: notebook-as-pdf-abirami
Version: 0.5.8
Summary: Jupyter extension to export notebooks as PDFs
Home-page: https://github.com/betatim/notebook-as-pdf
Author: Tim Head
Author-email: betatim@gmail.com
License: BSD3
Keywords: jupyter pdf export bundler
Requires-Python: >=3.7
License-File: LICENSE
Requires-Dist: nbconvert
Requires-Dist: pyppeteer
Requires-Dist: PyPDF2
